{
  "levelA": {
    "grid": [
      [1, 1, 1, 1, 1],
      [0, 0, 1, 0, 0],
      [1, 0, 1, 0, 1],
      [1, 0, 1, 1, 1],
      [0, 1, 0, 0, 1]
    ],
    "minSteps": 7
  },
  "levelB": {
    "grid": [
      [1, 0, 1, 0, 0],
      [0, 1, 1, 1, 1],
      [0, 0, 1, 1, 0],
      [0, 0, 1, 0, 0],
      [0, 1, 1, 1, 0]
    ],
    "minSteps": 8
  },
  "levelC": {
    "grid": [
      [1, 0, 0, 0, 0],
      [0, 1, 1, 0, 1],
      [1, 0, 0, 1, 1],
      [0, 0, 1, 1, 1],
      [1, 1, 0, 0, 0]
    ],
    "minSteps": 9
  }
}
